locks.py
locks-0.1.1.dist-info/LICENSE
locks-0.1.1.dist-info/METADATA
locks-0.1.1.dist-info/WHEEL
locks-0.1.1.dist-info/top_level.txt
locks-0.1.1.dist-info/RECORD
